LICENSE
README.md
setup.py
ovos_audio_metadata/__about__.py
ovos_audio_metadata/__init__.py
ovos_audio_metadata/api.py
ovos_audio_metadata/exceptions.py
ovos_audio_metadata/models.py
ovos_audio_metadata/utils.py
ovos_audio_metadata.egg-info/PKG-INFO
ovos_audio_metadata.egg-info/SOURCES.txt
ovos_audio_metadata.egg-info/dependency_links.txt
ovos_audio_metadata.egg-info/requires.txt
ovos_audio_metadata.egg-info/top_level.txt
ovos_audio_metadata.egg-info/zip-safe
ovos_audio_metadata/formats/__init__.py
ovos_audio_metadata/formats/flac.py
ovos_audio_metadata/formats/id3v1.py
ovos_audio_metadata/formats/id3v2.py
ovos_audio_metadata/formats/id3v2frames.py
ovos_audio_metadata/formats/mp3.py
ovos_audio_metadata/formats/mp4.py
ovos_audio_metadata/formats/mp4_tags.py
ovos_audio_metadata/formats/ogg.py
ovos_audio_metadata/formats/oggopus.py
ovos_audio_metadata/formats/oggvorbis.py
ovos_audio_metadata/formats/tables.py
ovos_audio_metadata/formats/vorbiscomments.py
ovos_audio_metadata/formats/wave.py
ovos_audio_metadata/tbm_utils/__init__.py
ovos_audio_metadata/tbm_utils/decorators.py
ovos_audio_metadata/tbm_utils/humanize.py
ovos_audio_metadata/tbm_utils/io.py
ovos_audio_metadata/tbm_utils/structures.py